bulktweetbyref/__init__.py
bulktweetbyref-0.1.0.dist-info/METADATA
bulktweetbyref-0.1.0.dist-info/WHEEL
bulktweetbyref-0.1.0.dist-info/top_level.txt
bulktweetbyref-0.1.0.dist-info/RECORD
