Metadata-Version: 2.4
Name: bulktweetbyref
Version: 0.1.0
Summary: bulk tweet fetcher
Author-email: Alex Mitch <alexmitch@example.com>
License: MIT
Classifier: Programming Language :: Python :: 3
Classifier: License :: OSI Approved :: MIT License
